LICENSE
MANIFEST.in
README.md
setup.cfg
setup.py
midbench/__init__.py
midbench/core.py
midbench/error.py
midbench/logger.py
midbench.egg-info/PKG-INFO
midbench.egg-info/SOURCES.txt
midbench.egg-info/dependency_links.txt
midbench.egg-info/requires.txt
midbench.egg-info/top_level.txt
midbench/envs/__init__.py
midbench/envs/registration.py
midbench/envs/airfoil/__init__.py
midbench/envs/airfoil/airfoil2d.py
midbench/envs/airfoil/airfoils_pred_cbegan_example.npy
midbench/envs/airfoil/config_opt.cfg
midbench/envs/airfoil/config_simu.cfg
midbench/envs/heatconduction/__init__.py
midbench/envs/heatconduction/designHeatconduction2d.py
midbench/envs/heatconduction/heatconduction2d.py
midbench/envs/heatconduction/simulateHeatconduction2d.py
midbench/utils/__init__.py
midbench/utils/colorize.py