Metadata-Version: 2.1
Name: midbench
Version: 0.1
Summary: The Maryland Inverse Design (MID) Benchmark Suite
Home-page: https://github.com/IDEALLab/midbench
Download-URL: https://github.com/IDEALLab/midbench/archive/refs/tags/v0.1-beta.tar.gz
Author: The Information for Design, Engineering, And Learning Laboratory
Author-email: fuge@umd.edu
License: MIT
Platform: UNKNOWN
Classifier: Development Status :: 3 - Alpha
Classifier: Topic :: Scientific/Engineering
Classifier: License :: OSI Approved :: MIT License
Classifier: Programming Language :: Python :: 3
Classifier: Programming Language :: Python :: 3.6
Classifier: Programming Language :: Python :: 3.7
Classifier: Programming Language :: Python :: 3.8
Classifier: Programming Language :: Python :: 3.9
Classifier: Programming Language :: Python :: 3.10
License-File: LICENSE
